{
  "Generic": {
    "antiGhostItemsAutoTriggerInterval": 10,
    "antiGhostItemsManualTrigger": {
      "keys": "",
      "settings": {
        "activate_on": "PRESS",
        "context": "INGAME",
        "allow_empty": false,
        "allow_extra_keys": false,
        "order_sensitive": true,
        "exclusive": false,
        "cancel": true
      }
    },
    "antiGhostItemsMode": "automatic",
    "autoDropInterval": 0,
    "autoReconnectTimer": 5,
    "daylightOverrideTime": 6000,
    "getTargetBlockPosition": {
      "keys": "",
      "settings": {
        "activate_on": "PRESS",
        "context": "INGAME",
        "allow_empty": false,
        "allow_extra_keys": false,
        "order_sensitive": true,
        "exclusive": false,
        "cancel": true
      }
    },
    "lowHealthThreshold": 6.0,
    "openConfigGui": {
      "keys": "J,C",
      "settings": {
        "activate_on": "PRESS",
        "context": "INGAME",
        "allow_empty": false,
        "allow_extra_keys": false,
        "order_sensitive": true,
        "exclusive": false,
        "cancel": true
      }
    },
    "targetBlockMaxTraceDistance": 100.0,
    "targetBlockPositionFormat": "I\u0027m tracing this position [x: {X},y: {Y}, z: {Z}]",
    "targetBlockPositionPrintMode": "private"
  },
  "Patch": {
    "disableLitematicaEasyPlaceFailTip": false
  },
  "List": {
    "listAutoDropBlackList": [
      "minecraft:bow",
      "minecraft:crossbow",
      "minecraft:diamond_axe",
      "minecraft:diamond_boots",
      "minecraft:diamond_chestplate",
      "minecraft:diamond_helmet",
      "minecraft:diamond_hoe",
      "minecraft:diamond_leggings",
      "minecraft:diamond_pickaxe",
      "minecraft:diamond_shovel",
      "minecraft:diamond_sword",
      "minecraft:elytra",
      "minecraft:enchanted_golden_apple",
      "minecraft:flint_and_steel",
      "minecraft:fishing_rod",
      "minecraft:golden_apple",
      "minecraft:golden_axe",
      "minecraft:golden_boots",
      "minecraft:golden_chestplate",
      "minecraft:golden_helmet",
      "minecraft:golden_hoe",
      "minecraft:golden_leggings",
      "minecraft:golden_pickaxe",
      "minecraft:golden_shovel",
      "minecraft:golden_sword",
      "minecraft:iron_axe",
      "minecraft:iron_boots",
      "minecraft:iron_chestplate",
      "minecraft:iron_helmet",
      "minecraft:iron_hoe",
      "minecraft:iron_leggings",
      "minecraft:iron_pickaxe",
      "minecraft:iron_shovel",
      "minecraft:iron_sword",
      "minecraft:netherite_axe",
      "minecraft:netherite_boots",
      "minecraft:netherite_chestplate",
      "minecraft:netherite_helmet",
      "minecraft:netherite_hoe",
      "minecraft:netherite_leggings",
      "minecraft:netherite_pickaxe",
      "minecraft:netherite_shovel",
      "minecraft:netherite_sword",
      "minecraft:shears",
      "minecraft:shield",
      "minecraft:totem_of_undying",
      "minecraft:trident",
      "minecraft:turtle_helmet"
    ],
    "listAutoDropType": "whiteList",
    "listAutoDropWhiteList": [
      "minecraft:stone",
      "minecraft:dirt",
      "minecraft:cobblestone",
      "minecraft:gravel",
      "minecraft:rotten_flesh"
    ],
    "listDisableClientEntityUpdates": [
      "tnt"
    ],
    "listDisableClientEntityRendering": [
      "tnt"
    ]
  },
  "Color": {
    "colorBlockOutside": "#FF3394FF",
    "colorGuiStart": "#C00F0F0F",
    "colorGuiStop": "#D00F0F0F",
    "colorSidebarContent": "#4C000000",
    "colorSidebarTitle": "#66000000",
    "colorWaterOpen": "#7F00FF00",
    "colorWaterShallow": "#7FFF0000"
  },
  "Disable": {
    "disableClientBlockEvents": false,
    "disableClientEntityInListUpdates": false,
    "disableClientEntityTNTUpdates": false,
    "disableClientEntityWitherUpdates": false,
    "disableClientEntityZombieVillagerUpdates": false,
    "disableClientEntityInListRendering": false,
    "disableEntityTNTRendering": false,
    "disableEntityZombieVillagerRendering": false,
    "disableEntityWitherRendering": false,
    "disableGuiShadowLayer": true,
    "disableRenderBossBar": false,
    "disableRenderOverlayFire": true,
    "disableRenderOverlayPumpkin": true,
    "disableRenderScoreboard": false,
    "disableRenderToast": false,
    "disableSlowdown": false
  },
  "DisableHotkey": {
    "disableClientBlockEvents": {
      "keys": "",
      "settings": {
        "activate_on": "PRESS",
        "context": "INGAME",
        "allow_empty": false,
        "allow_extra_keys": false,
        "order_sensitive": true,
        "exclusive": false,
        "cancel": true
      }
    },
    "disableClientEntityInListUpdates": {
      "keys": "",
      "settings": {
        "activate_on": "PRESS",
        "context": "INGAME",
        "allow_empty": false,
        "allow_extra_keys": false,
        "order_sensitive": true,
        "exclusive": false,
        "cancel": true
      }
    },
    "disableClientEntityTNTUpdates": {
      "keys": "",
      "settings": {
        "activate_on": "PRESS",
        "context": "INGAME",
        "allow_empty": false,
        "allow_extra_keys": false,
        "order_sensitive": true,
        "exclusive": false,
        "cancel": true
      }
    },
    "disableClientEntityWitherUpdates": {
      "keys": "",
      "settings": {
        "activate_on": "PRESS",
        "context": "INGAME",
        "allow_empty": false,
        "allow_extra_keys": false,
        "order_sensitive": true,
        "exclusive": false,
        "cancel": true
      }
    },
    "disableClientEntityZombieVillagerUpdates": {
      "keys": "",
      "settings": {
        "activate_on": "PRESS",
        "context": "INGAME",
        "allow_empty": false,
        "allow_extra_keys": false,
        "order_sensitive": true,
        "exclusive": false,
        "cancel": true
      }
    },
    "disableClientEntityInListRendering": {
      "keys": "",
      "settings": {
        "activate_on": "PRESS",
        "context": "INGAME",
        "allow_empty": false,
        "allow_extra_keys": false,
        "order_sensitive": true,
        "exclusive": false,
        "cancel": true
      }
    },
    "disableEntityTNTRendering": {
      "keys": "",
      "settings": {
        "activate_on": "PRESS",
        "context": "INGAME",
        "allow_empty": false,
        "allow_extra_keys": false,
        "order_sensitive": true,
        "exclusive": false,
        "cancel": true
      }
    },
    "disableEntityZombieVillagerRendering": {
      "keys": "",
      "settings": {
        "activate_on": "PRESS",
        "context": "INGAME",
        "allow_empty": false,
        "allow_extra_keys": false,
        "order_sensitive": true,
        "exclusive": false,
        "cancel": true
      }
    },
    "disableEntityWitherRendering": {
      "keys": "",
      "settings": {
        "activate_on": "PRESS",
        "context": "INGAME",
        "allow_empty": false,
        "allow_extra_keys": false,
        "order_sensitive": true,
        "exclusive": false,
        "cancel": true
      }
    },
    "disableGuiShadowLayer": {
      "keys": "",
      "settings": {
        "activate_on": "PRESS",
        "context": "INGAME",
        "allow_empty": false,
        "allow_extra_keys": false,
        "order_sensitive": true,
        "exclusive": false,
        "cancel": true
      }
    },
    "disableRenderBossBar": {
      "keys": "",
      "settings": {
        "activate_on": "PRESS",
        "context": "INGAME",
        "allow_empty": false,
        "allow_extra_keys": false,
        "order_sensitive": true,
        "exclusive": false,
        "cancel": true
      }
    },
    "disableRenderOverlayFire": {
      "keys": "",
      "settings": {
        "activate_on": "PRESS",
        "context": "INGAME",
        "allow_empty": false,
        "allow_extra_keys": false,
        "order_sensitive": true,
        "exclusive": false,
        "cancel": true
      }
    },
    "disableRenderOverlayPumpkin": {
      "keys": "",
      "settings": {
        "activate_on": "PRESS",
        "context": "INGAME",
        "allow_empty": false,
        "allow_extra_keys": false,
        "order_sensitive": true,
        "exclusive": false,
        "cancel": true
      }
    },
    "disableRenderScoreboard": {
      "keys": "",
      "settings": {
        "activate_on": "PRESS",
        "context": "INGAME",
        "allow_empty": false,
        "allow_extra_keys": false,
        "order_sensitive": true,
        "exclusive": false,
        "cancel": true
      }
    },
    "disableRenderToast": {
      "keys": "",
      "settings": {
        "activate_on": "PRESS",
        "context": "INGAME",
        "allow_empty": false,
        "allow_extra_keys": false,
        "order_sensitive": true,
        "exclusive": false,
        "cancel": true
      }
    },
    "disableSlowdown": {
      "keys": "",
      "settings": {
        "activate_on": "PRESS",
        "context": "INGAME",
        "allow_empty": false,
        "allow_extra_keys": false,
        "order_sensitive": true,
        "exclusive": false,
        "cancel": true
      }
    }
  },
  "Feature": {
    "featureAntiGhostItems": true,
    "featureAutoDrop": false,
    "featureAutoReconnect": false,
    "featureAutoRespawn": true,
    "featureCustomBlockOutsideColor": true,
    "featureCustomGuiBackgroundColor": false,
    "featureCustomSidebarBackgroundColor": false,
    "featureGlobalEventListener": false,
    "featureDaylightOverride": false,
    "featureGetTargetBlockPosition": false,
    "featureLowHealthWarning": false,
    "featureOpenWaterHelper": false,
    "featureUnfocusedCPU": true
  },
  "FeatureHotkey": {
    "featureAntiGhostItems": {
      "keys": "",
      "settings": {
        "activate_on": "PRESS",
        "context": "INGAME",
        "allow_empty": false,
        "allow_extra_keys": false,
        "order_sensitive": true,
        "exclusive": false,
        "cancel": true
      }
    },
    "featureAutoDrop": {
      "keys": "",
      "settings": {
        "activate_on": "PRESS",
        "context": "INGAME",
        "allow_empty": false,
        "allow_extra_keys": false,
        "order_sensitive": true,
        "exclusive": false,
        "cancel": true
      }
    },
    "featureAutoReconnect": {
      "keys": "",
      "settings": {
        "activate_on": "PRESS",
        "context": "INGAME",
        "allow_empty": false,
        "allow_extra_keys": false,
        "order_sensitive": true,
        "exclusive": false,
        "cancel": true
      }
    },
    "featureAutoRespawn": {
      "keys": "",
      "settings": {
        "activate_on": "PRESS",
        "context": "INGAME",
        "allow_empty": false,
        "allow_extra_keys": false,
        "order_sensitive": true,
        "exclusive": false,
        "cancel": true
      }
    },
    "featureCustomBlockOutsideColor": {
      "keys": "",
      "settings": {
        "activate_on": "PRESS",
        "context": "INGAME",
        "allow_empty": false,
        "allow_extra_keys": false,
        "order_sensitive": true,
        "exclusive": false,
        "cancel": true
      }
    },
    "featureCustomGuiBackgroundColor": {
      "keys": "",
      "settings": {
        "activate_on": "PRESS",
        "context": "INGAME",
        "allow_empty": false,
        "allow_extra_keys": false,
        "order_sensitive": true,
        "exclusive": false,
        "cancel": true
      }
    },
    "featureCustomSidebarBackgroundColor": {
      "keys": "",
      "settings": {
        "activate_on": "PRESS",
        "context": "INGAME",
        "allow_empty": false,
        "allow_extra_keys": false,
        "order_sensitive": true,
        "exclusive": false,
        "cancel": true
      }
    },
    "featureGlobalEventListener": {
      "keys": "",
      "settings": {
        "activate_on": "PRESS",
        "context": "INGAME",
        "allow_empty": false,
        "allow_extra_keys": false,
        "order_sensitive": true,
        "exclusive": false,
        "cancel": true
      }
    },
    "featureDaylightOverride": {
      "keys": "",
      "settings": {
        "activate_on": "PRESS",
        "context": "INGAME",
        "allow_empty": false,
        "allow_extra_keys": false,
        "order_sensitive": true,
        "exclusive": false,
        "cancel": true
      }
    },
    "featureGetTargetBlockPosition": {
      "keys": "",
      "settings": {
        "activate_on": "PRESS",
        "context": "INGAME",
        "allow_empty": false,
        "allow_extra_keys": false,
        "order_sensitive": true,
        "exclusive": false,
        "cancel": true
      }
    },
    "featureLowHealthWarning": {
      "keys": "",
      "settings": {
        "activate_on": "PRESS",
        "context": "INGAME",
        "allow_empty": false,
        "allow_extra_keys": false,
        "order_sensitive": true,
        "exclusive": false,
        "cancel": true
      }
    },
    "featureOpenWaterHelper": {
      "keys": "",
      "settings": {
        "activate_on": "PRESS",
        "context": "INGAME",
        "allow_empty": false,
        "allow_extra_keys": false,
        "order_sensitive": true,
        "exclusive": false,
        "cancel": true
      }
    },
    "featureUnfocusedCPU": {
      "keys": "",
      "settings": {
        "activate_on": "PRESS",
        "context": "INGAME",
        "allow_empty": false,
        "allow_extra_keys": false,
        "order_sensitive": true,
        "exclusive": false,
        "cancel": true
      }
    }
  }
}